AUTHORS.rst
CONTRIBUTING.rst
HISTORY.rst
LICENSE
MANIFEST.in
README.rst
setup.cfg
setup.py
docs/Makefile
docs/authors.rst
docs/conf.py
docs/contributing.rst
docs/history.rst
docs/index.rst
docs/installation.rst
docs/make.bat
docs/readme.rst
docs/usage.rst
simple_hi/__init__.py
simple_hi/simple_hi.py
simple_hi.egg-info/PKG-INFO
simple_hi.egg-info/SOURCES.txt
simple_hi.egg-info/dependency_links.txt
simple_hi.egg-info/not-zip-safe
simple_hi.egg-info/top_level.txt
tests/__init__.py
tests/test_simple_hi.py